spawner/__init__.py
spawner/execution.py
spawner/forecasting.py
spawner/indicators.py
spawner/metrics.py
spawner/nlp.py
spawner/options.py
spawner/portfolio.py
spawner/signal.py
spawner/spawner.py
spawner/statistics.py
spawner/__pycache__/__init__.cpython-37.pyc
spawner/__pycache__/indicators.cpython-37.pyc
spawner/__pycache__/metrics.cpython-37.pyc
spawner/__pycache__/nlp.cpython-37.pyc
spawner/__pycache__/signal.cpython-37.pyc
spawner/__pycache__/spawner.cpython-37.pyc
spawner/__pycache__/statistics.cpython-37.pyc
spawner-0.2.4.dist-info/METADATA
spawner-0.2.4.dist-info/WHEEL
spawner-0.2.4.dist-info/top_level.txt
spawner-0.2.4.dist-info/RECORD
