Metadata-Version: 2.1
Name: spawner
Version: 0.2.4
Summary: Spawner API
Home-page: https://github.com/spawner/python-sdk
Author: Spawner Team
Author-email: info@spawner.ai
License: UNKNOWN
Keywords: Spawner,Python,API
Platform: UNKNOWN
Classifier: Development Status :: 3 - Alpha
Classifier: Intended Audience :: Developers
Requires-Dist: requests
Requires-Dist: pandas
